[
  {
    "projectImage": "/assets/images/services/unreal-project1.jpg",
    "projectTitle": "Car Racing Game",
    "projectDescription": "We’ve designed and developed tons of exciting titles that make gameplay fun for everyone."
  },
  {
    "projectImage": "/assets/images/services/unreal-project2.jpg",
    "projectTitle": "Car Racing Game",
    "projectDescription": "We’ve designed and developed tons of exciting titles that make gameplay fun for everyone."
  },
  {
    "projectImage": "/assets/images/services/unreal-project3.jpg",
    "projectTitle": "Car Racing Game",
    "projectDescription": "We’ve designed and developed tons of exciting titles that make gameplay fun for everyone."
  }
]