[
  {
    "galleryImage": "/assets/images/company/gallery-image1.jpg",
    "galleryTitle": "Playing Games",
    "galleryDescription": "Lorem ipsum dolor sit amet consectetur. Nisl est a ornare nisl at."
  },
  {
    "galleryImage": "/assets/images/company/gallery-image2.jpg",
    "galleryTitle": "Playing Games",
    "galleryDescription": "Lorem ipsum dolor sit amet consectetur. Nisl est a ornare nisl at."
  },
  {
    "galleryImage": "/assets/images/company/gallery-image3.jpg",
    "galleryTitle": "Playing Games",
    "galleryDescription": "Lorem ipsum dolor sit amet consectetur. Nisl est a ornare nisl at."
  },
  {
    "galleryImage": "/assets/images/company/gallery-image4.jpg",
    "galleryTitle": "Playing Games",
    "galleryDescription": "Lorem ipsum dolor sit amet consectetur. Nisl est a ornare nisl at."
  },
  {
    "galleryImage": "/assets/images/company/gallery-image1.jpg",
    "galleryTitle": "Playing Games",
    "galleryDescription": "Lorem ipsum dolor sit amet consectetur. Nisl est a ornare nisl at."
  },
  {
    "galleryImage": "/assets/images/company/gallery-image2.jpg",
    "galleryTitle": "Playing Games",
    "galleryDescription": "Lorem ipsum dolor sit amet consectetur. Nisl est a ornare nisl at."
  },
  {
    "galleryImage": "/assets/images/company/gallery-image3.jpg",
    "galleryTitle": "Playing Games",
    "galleryDescription": "Lorem ipsum dolor sit amet consectetur. Nisl est a ornare nisl at."
  },
  {
    "galleryImage": "/assets/images/company/gallery-image4.jpg",
    "galleryTitle": "Playing Games",
    "galleryDescription": "Lorem ipsum dolor sit amet consectetur. Nisl est a ornare nisl at."
  }
]